ephemeral_port_reserve.py
ephemeral_port_reserve-1.1.4.dist-info/LICENSE
ephemeral_port_reserve-1.1.4.dist-info/METADATA
ephemeral_port_reserve-1.1.4.dist-info/WHEEL
ephemeral_port_reserve-1.1.4.dist-info/entry_points.txt
ephemeral_port_reserve-1.1.4.dist-info/top_level.txt
ephemeral_port_reserve-1.1.4.dist-info/RECORD
